pensity/__init__.py
pensity/common-endpoints.txt
pensity/pensity.py
pensity-1.0.0.dist-info/licenses/LICENSE
pensity-1.0.0.dist-info/METADATA
pensity-1.0.0.dist-info/WHEEL
pensity-1.0.0.dist-info/entry_points.txt
pensity-1.0.0.dist-info/top_level.txt
pensity-1.0.0.dist-info/RECORD
