Metadata-Version: 2.4
Name: pensity
Version: 1.0.0
Summary: Advanced JavaScript File Discovery and Security Analysis Tool
Author-email: iosec <noreply@github.com>
Project-URL: Homepage, https://github.com/iosec/pensity
Project-URL: Bug Tracker, https://github.com/iosec/pensity/issues
Keywords: security,javascript,analysis,vulnerability,scanning,osint,web-security
Classifier: Development Status :: 4 - Beta
Classifier: Intended Audience :: Developers
Classifier: Intended Audience :: Information Technology
Classifier: Topic :: Security
Classifier: Topic :: Internet :: WWW/HTTP
Classifier: License :: OSI Approved :: MIT License
Classifier: Programming Language :: Python :: 3
Classifier: Programming Language :: Python :: 3.8
Classifier: Programming Language :: Python :: 3.9
Classifier: Programming Language :: Python :: 3.10
Classifier: Programming Language :: Python :: 3.11
Classifier: Programming Language :: Python :: 3.12
Requires-Python: >=3.8
License-File: LICENSE
Requires-Dist: requests>=2.25.0
Requires-Dist: beautifulsoup4>=4.9.0
Requires-Dist: urllib3>=1.26.0
Provides-Extra: llm
Requires-Dist: llm>=0.13.0; extra == "llm"
Dynamic: license-file
